customGUI/__init__.py
customGUI/form_creator.py
customGUI/form_loader.py
customGUI/objects/__init__.py
customGUI/objects/base_icon.py
customGUI/objects/button.py
customGUI/objects/canvas.py
customGUI/objects/form.py
customGUI/objects/label.py
customGUI/objects/textbox.py
customGUI/objects/utils.py
customGUI/tools/__init__.py
customGUI/tools/exception_handler.py
customGUI/tools/listener.py
customGUI/tools/memory.py
customGUI/tools/specification_viewer.py
customGUI/tools/toolbar.py
customGUI-1.0.7.dist-info/LICENCE
customGUI-1.0.7.dist-info/METADATA
customGUI-1.0.7.dist-info/WHEEL
customGUI-1.0.7.dist-info/top_level.txt
customGUI-1.0.7.dist-info/RECORD
